logcatframe/README.MD
logcatframe/__init__.py
logcatframe/requirements.txt
logcatframe/thirdparty.json
logcatframe-0.10.dist-info/LICENSE.rst
logcatframe-0.10.dist-info/METADATA
logcatframe-0.10.dist-info/WHEEL
logcatframe-0.10.dist-info/top_level.txt
logcatframe-0.10.dist-info/RECORD
