Metadata-Version: 2.1
Name: logcatframe
Version: 0.10
Summary: Class for capturing and parsing Android device logs using ADB.
Home-page: https://github.com/hansalemaos/logcatframe
Author: Johannes Fischer
Author-email: aulasparticularesdealemaosp@gmail.com
License: MIT
Keywords: python,logcat
Classifier: Development Status :: 4 - Beta
Classifier: Programming Language :: Python :: 3 :: Only
Classifier: Programming Language :: Python :: 3.10
Classifier: Topic :: Software Development :: Libraries :: Python Modules
Classifier: Topic :: Utilities
License-File: LICENSE.rst
Requires-Dist: flatten-everything
Requires-Dist: regex
